JSONGrapher/JSONRecordCreator.py
JSONGrapher/UnitPytesting.py
JSONGrapher/UnitpyCustomUnitsTesting.py
JSONGrapher/__init__.py
JSONGrapher/drag_and_drop_gui.py
JSONGrapher/equation_creator.py
JSONGrapher/equation_evaluator.py
JSONGrapher/units_list.py
JSONGrapher/version.py
JSONGrapher/styles/__init__.py
JSONGrapher/styles/layout_styles_library.py
JSONGrapher/styles/trace_styles_collection_library.py
jsongrapher-5.1.data/data/LICENSE.txt
jsongrapher-5.1.data/data/README.md
jsongrapher-5.1.dist-info/LICENSE.txt
jsongrapher-5.1.dist-info/METADATA
jsongrapher-5.1.dist-info/WHEEL
jsongrapher-5.1.dist-info/top_level.txt
jsongrapher-5.1.dist-info/RECORD
