Metadata-Version: 2.1
Name: jsongrapher
Version: 5.1
Summary: The python version of JSONGrapher with tools for creating JSONGrapher Records.
Home-page: https://github.com/AdityaSavara/jsongrapher-py
Author: Aditya Savara
Author-email: AdityaSavara2008@u.northwestern.edu
License: BSD-3-Clause
Classifier: License :: OSI Approved :: BSD License
Classifier: Programming Language :: Python
Classifier: Programming Language :: Python :: 3
Classifier: Programming Language :: Python :: 3.6
Classifier: Programming Language :: Python :: Implementation :: CPython
Classifier: Programming Language :: Python :: Implementation :: PyPy
Requires-Python: >=3.0.0
License-File: LICENSE.txt
Requires-Dist: numpy>=1.26
Provides-Extra: complete
Requires-Dist: matplotlib; extra == "complete"
Requires-Dist: plotly; extra == "complete"
Requires-Dist: unitpy; extra == "complete"
Requires-Dist: tkinterdnd2; extra == "complete"
Requires-Dist: urllib; extra == "complete"
Requires-Dist: json-equationer; extra == "complete"
